obspec_utils/__init__.py
obspec_utils/_version.py
obspec_utils/file_handlers.py
obspec_utils/py.typed
obspec_utils/registry.py
obspec_utils/typing.py
obspec_utils-0.4.1.dist-info/METADATA
obspec_utils-0.4.1.dist-info/WHEEL
obspec_utils-0.4.1.dist-info/licenses/LICENSE
obspec_utils-0.4.1.dist-info/RECORD
