Metadata-Version: 2.4
Name: obspec-utils
Version: 0.4.1
Summary: Utilities for interacting with object storage, based on obspec
Project-URL: Documentation, https://obspec-utils.readthedocs.io
Project-URL: Issues, https://github.com/virtual-zarr/obspec-utils/issues
Project-URL: Source, https://github.com/virtual-zarr/obspec-utils
Author-email: Max Jones <14077947+maxrjones@users.noreply.github.com>
License-Expression: Apache-2.0
License-File: LICENSE
Classifier: Development Status :: 4 - Beta
Classifier: Programming Language :: Python
Classifier: Programming Language :: Python :: 3.11
Classifier: Programming Language :: Python :: 3.12
Classifier: Programming Language :: Python :: 3.13
Classifier: Programming Language :: Python :: 3.14
Classifier: Programming Language :: Python :: Implementation :: CPython
Classifier: Programming Language :: Python :: Implementation :: PyPy
Requires-Python: >=3.11
Requires-Dist: obspec
Requires-Dist: obstore
